{
    "sourceVersion": "9.0.84",
    "activateOnDeploy": false,
    "inspformnum": "1020",
    "revision": 2,
    "name": "FMP Construction Site Perimeter Inspection Checklist",
    "instructions": "",
    "reason": "Add date/time",
    "type": "Condition Assessment",
    "readconfirmation": false,
    "audioguided": false,
    "questions": [
        {
            "inspquestionnum": "1738",
            "inspformnum": "1020",
            "description": "Weather Conditions",
            "information": "",
            "sequence": 1,
            "groupseq": 1,
            "required": false,
            "fields": []
        },
        {
            "inspquestionnum": "1739",
            "inspformnum": "1020",
            "description": "Perimeter fencing is intact, secure, and free of damage (no gaps, leaning sections, or easy entry)",
            "information": "",
            "groupid": 2,
            "sequence": 1,
            "groupseq": 2.001,
            "required": false,
            "fields": [
                {
                    "inspfieldnum": "2112",
                    "inspquestionnum": "1739",
                    "inspformnum": "1020",
                    "fieldtype": "SO",
                    "description": "Perimeter fencing",
                    "sequence": 1,
                    "required": false,
                    "initiallabel": "",
                    "endlabel": "",
                    "metername": "",
                    "metertype": "",
                    "showdate": false,
                    "showtime": false,
                    "doctype": "",
                    "visible": true,
                    "domainid": "",
                    "domaintype": "",
                    "options": [
                        {
                            "inspfieldnum": "2112",
                            "inspquestionnum": "1739",
                            "inspformnum": "1020",
                            "description": "Compliant",
                            "sequence": 1,
                            "inspectorfeedback": "",
                            "requireaction": false,
                            "color": "",
                            "icon": ""
                        },
                        {
                            "inspfieldnum": "2112",
                            "inspquestionnum": "1739",
                            "inspformnum": "1020",
                            "description": "Not Applicable",
                            "sequence": 2,
                            "inspectorfeedback": "",
                            "requireaction": false,
                            "color": "",
                            "icon": ""
                        },
                        {
                            "inspfieldnum": "2112",
                            "inspquestionnum": "1739",
                            "inspformnum": "1020",
                            "description": "Non-Compliant",
                            "sequence": 3,
                            "inspectorfeedback": "",
                            "requireaction": true,
                            "color": "",
                            "icon": ""
                        }
                    ]
                },
                {
                    "inspfieldnum": "2113",
                    "inspquestionnum": "1739",
                    "inspformnum": "1020",
                    "fieldtype": "TR",
                    "description": "Details",
                    "sequence": 2,
                    "required": false,
                    "initiallabel": "",
                    "endlabel": "",
                    "metername": "",
                    "metertype": "",
                    "showdate": false,
                    "showtime": false,
                    "doctype": "",
                    "visible": false,
                    "domainid": "",
                    "domaintype": "",
                    "options": []
                }
            ]
        },
        {
            "inspquestionnum": "1740",
            "inspformnum": "1020",
            "description": "All gates are closed and secured outside of operational hours, preventing unauthorized entry.",
            "information": "",
            "groupid": 2,
            "sequence": 2,
            "groupseq": 2.002,
            "required": false,
            "fields": [
                {
                    "inspfieldnum": "2114",
                    "inspquestionnum": "1740",
                    "inspformnum": "1020",
                    "fieldtype": "SO",
                    "description": "Gates",
                    "sequence": 1,
                    "required": false,
                    "initiallabel": "",
                    "endlabel": "",
                    "metername": "",
                    "metertype": "",
                    "showdate": false,
                    "showtime": false,
                    "doctype": "",
                    "visible": true,
                    "domainid": "",
                    "domaintype": "",
                    "options": [
                        {
                            "inspfieldnum": "2114",
                            "inspquestionnum": "1740",
                            "inspformnum": "1020",
                            "description": "Compliant",
                            "sequence": 1,
                            "inspectorfeedback": "",
                            "requireaction": false,
                            "color": "",
                            "icon": ""
                        },
                        {
                            "inspfieldnum": "2114",
                            "inspquestionnum": "1740",
                            "inspformnum": "1020",
                            "description": "Not Applicable",
                            "sequence": 2,
                            "inspectorfeedback": "",
                            "requireaction": false,
                            "color": "",
                            "icon": ""
                        },
                        {
                            "inspfieldnum": "2114",
                            "inspquestionnum": "1740",
                            "inspformnum": "1020",
                            "description": "Non-Compliant",
                            "sequence": 3,
                            "inspectorfeedback": "",
                            "requireaction": true,
                            "color": "",
                            "icon": ""
                        }
                    ]
                },
                {
                    "inspfieldnum": "2115",
                    "inspquestionnum": "1740",
                    "inspformnum": "1020",
                    "fieldtype": "TR",
                    "description": "Details",
                    "sequence": 2,
                    "required": false,
                    "initiallabel": "",
                    "endlabel": "",
                    "metername": "",
                    "metertype": "",
                    "showdate": false,
                    "showtime": false,
                    "doctype": "",
                    "visible": false,
                    "domainid": "",
                    "domaintype": "",
                    "options": []
                }
            ]
        },
        {
            "inspquestionnum": "1741",
            "inspformnum": "1020",
            "description": "\"No Trespassing\" or \"Authorized Personnel Only\" signage is clearly visible and correctly positioned.",
            "information": "",
            "groupid": 2,
            "sequence": 3,
            "groupseq": 2.003,
            "required": false,
            "fields": [
                {
                    "inspfieldnum": "2116",
                    "inspquestionnum": "1741",
                    "inspformnum": "1020",
                    "fieldtype": "SO",
                    "description": "\"No Trespassing\" or \"Authorized Personnel Only\" Signage",
                    "sequence": 1,
                    "required": false,
                    "initiallabel": "",
                    "endlabel": "",
                    "metername": "",
                    "metertype": "",
                    "showdate": false,
                    "showtime": false,
                    "doctype": "",
                    "visible": true,
                    "domainid": "",
                    "domaintype": "",
                    "options": [
                        {
                            "inspfieldnum": "2116",
                            "inspquestionnum": "1741",
                            "inspformnum": "1020",
                            "description": "Compliant",
                            "sequence": 1,
                            "inspectorfeedback": "",
                            "requireaction": false,
                            "color": "",
                            "icon": ""
                        },
                        {
                            "inspfieldnum": "2116",
                            "inspquestionnum": "1741",
                            "inspformnum": "1020",
                            "description": "Not Applicable",
                            "sequence": 2,
                            "inspectorfeedback": "",
                            "requireaction": false,
                            "color": "",
                            "icon": ""
                        },
                        {
                            "inspfieldnum": "2116",
                            "inspquestionnum": "1741",
                            "inspformnum": "1020",
                            "description": "Non-Compliant",
                            "sequence": 3,
                            "inspectorfeedback": "",
                            "requireaction": true,
                            "color": "",
                            "icon": ""
                        }
                    ]
                },
                {
                    "inspfieldnum": "2117",
                    "inspquestionnum": "1741",
                    "inspformnum": "1020",
                    "fieldtype": "TR",
                    "description": "Details",
                    "sequence": 2,
                    "required": false,
                    "initiallabel": "",
                    "endlabel": "",
                    "metername": "",
                    "metertype": "",
                    "showdate": false,
                    "showtime": false,
                    "doctype": "",
                    "visible": false,
                    "domainid": "",
                    "domaintype": "",
                    "options": []
                }
            ]
        },
        {
            "inspquestionnum": "1742",
            "inspformnum": "1020",
            "description": "Danger/Hazard warning signs (e.g., \"Hard Hat Area\", \"Construction Zone\") are at all access points",
            "information": "",
            "groupid": 2,
            "sequence": 4,
            "groupseq": 2.004,
            "required": false,
            "fields": [
                {
                    "inspfieldnum": "2118",
                    "inspquestionnum": "1742",
                    "inspformnum": "1020",
                    "fieldtype": "SO",
                    "description": "Danger/Hazard warning signs",
                    "sequence": 1,
                    "required": false,
                    "initiallabel": "",
                    "endlabel": "",
                    "metername": "",
                    "metertype": "",
                    "showdate": false,
                    "showtime": false,
                    "doctype": "",
                    "visible": true,
                    "domainid": "",
                    "domaintype": "",
                    "options": [
                        {
                            "inspfieldnum": "2118",
                            "inspquestionnum": "1742",
                            "inspformnum": "1020",
                            "description": "Compliant",
                            "sequence": 1,
                            "inspectorfeedback": "",
                            "requireaction": false,
                            "color": "",
                            "icon": ""
                        },
                        {
                            "inspfieldnum": "2118",
                            "inspquestionnum": "1742",
                            "inspformnum": "1020",
                            "description": "Not Applicable",
                            "sequence": 2,
                            "inspectorfeedback": "",
                            "requireaction": false,
                            "color": "",
                            "icon": ""
                        },
                        {
                            "inspfieldnum": "2118",
                            "inspquestionnum": "1742",
                            "inspformnum": "1020",
                            "description": "Non-Compliant",
                            "sequence": 3,
                            "inspectorfeedback": "",
                            "requireaction": true,
                            "color": "",
                            "icon": ""
                        }
                    ]
                },
                {
                    "inspfieldnum": "2119",
                    "inspquestionnum": "1742",
                    "inspformnum": "1020",
                    "fieldtype": "TR",
                    "description": "Details",
                    "sequence": 2,
                    "required": false,
                    "initiallabel": "",
                    "endlabel": "",
                    "metername": "",
                    "metertype": "",
                    "showdate": false,
                    "showtime": false,
                    "doctype": "",
                    "visible": false,
                    "domainid": "",
                    "domaintype": "",
                    "options": []
                }
            ]
        },
        {
            "inspquestionnum": "1743",
            "inspformnum": "1020",
            "description": "No evidence of unauthorized entry or vandalism (e.g., cut fences, broken locks)",
            "information": "",
            "groupid": 2,
            "sequence": 5,
            "groupseq": 2.005,
            "required": false,
            "fields": [
                {
                    "inspfieldnum": "2120",
                    "inspquestionnum": "1743",
                    "inspformnum": "1020",
                    "fieldtype": "SO",
                    "description": "Unauthorized entry",
                    "sequence": 1,
                    "required": false,
                    "initiallabel": "",
                    "endlabel": "",
                    "metername": "",
                    "metertype": "",
                    "showdate": false,
                    "showtime": false,
                    "doctype": "",
                    "visible": true,
                    "domainid": "",
                    "domaintype": "",
                    "options": [
                        {
                            "inspfieldnum": "2120",
                            "inspquestionnum": "1743",
                            "inspformnum": "1020",
                            "description": "Compliant",
                            "sequence": 1,
                            "inspectorfeedback": "",
                            "requireaction": false,
                            "color": "",
                            "icon": ""
                        },
                        {
                            "inspfieldnum": "2120",
                            "inspquestionnum": "1743",
                            "inspformnum": "1020",
                            "description": "Not Applicable",
                            "sequence": 2,
                            "inspectorfeedback": "",
                            "requireaction": false,
                            "color": "",
                            "icon": ""
                        },
                        {
                            "inspfieldnum": "2120",
                            "inspquestionnum": "1743",
                            "inspformnum": "1020",
                            "description": "Non-Compliant",
                            "sequence": 3,
                            "inspectorfeedback": "",
                            "requireaction": true,
                            "color": "",
                            "icon": ""
                        }
                    ]
                },
                {
                    "inspfieldnum": "2121",
                    "inspquestionnum": "1743",
                    "inspformnum": "1020",
                    "fieldtype": "TR",
                    "description": "Details",
                    "sequence": 2,
                    "required": false,
                    "initiallabel": "",
                    "endlabel": "",
                    "metername": "",
                    "metertype": "",
                    "showdate": false,
                    "showtime": false,
                    "doctype": "",
                    "visible": false,
                    "domainid": "",
                    "domaintype": "",
                    "options": []
                }
            ]
        },
        {
            "inspquestionnum": "1744",
            "inspformnum": "1020",
            "description": "Clear and safe pedestrian pathways are maintained outside the perimeter (no obstructions, debris)",
            "information": "",
            "groupid": 3,
            "sequence": 1,
            "groupseq": 3.001,
            "required": false,
            "fields": [
                {
                    "inspfieldnum": "2122",
                    "inspquestionnum": "1744",
                    "inspformnum": "1020",
                    "fieldtype": "SO",
                    "description": "Pedestrian pathways",
                    "sequence": 1,
                    "required": false,
                    "initiallabel": "",
                    "endlabel": "",
                    "metername": "",
                    "metertype": "",
                    "showdate": false,
                    "showtime": false,
                    "doctype": "",
                    "visible": true,
                    "domainid": "",
                    "domaintype": "",
                    "options": [
                        {
                            "inspfieldnum": "2122",
                            "inspquestionnum": "1744",
                            "inspformnum": "1020",
                            "description": "Compliant",
                            "sequence": 1,
                            "inspectorfeedback": "",
                            "requireaction": false,
                            "color": "",
                            "icon": ""
                        },
                        {
                            "inspfieldnum": "2122",
                            "inspquestionnum": "1744",
                            "inspformnum": "1020",
                            "description": "Not Applicable",
                            "sequence": 2,
                            "inspectorfeedback": "",
                            "requireaction": false,
                            "color": "",
                            "icon": ""
                        },
                        {
                            "inspfieldnum": "2122",
                            "inspquestionnum": "1744",
                            "inspformnum": "1020",
                            "description": "Non-Compliant",
                            "sequence": 3,
                            "inspectorfeedback": "",
                            "requireaction": true,
                            "color": "",
                            "icon": ""
                        }
                    ]
                },
                {
                    "inspfieldnum": "2123",
                    "inspquestionnum": "1744",
                    "inspformnum": "1020",
                    "fieldtype": "TR",
                    "description": "Details",
                    "sequence": 2,
                    "required": false,
                    "initiallabel": "",
                    "endlabel": "",
                    "metername": "",
                    "metertype": "",
                    "showdate": false,
                    "showtime": false,
                    "doctype": "",
                    "visible": false,
                    "domainid": "",
                    "domaintype": "",
                    "options": []
                }
            ]
        },
        {
            "inspquestionnum": "1745",
            "inspformnum": "1020",
            "description": "Designated pedestrian detours (if any) are clearly marked, well-lit, safely navigable.",
            "information": "",
            "groupid": 3,
            "sequence": 2,
            "groupseq": 3.002,
            "required": false,
            "fields": [
                {
                    "inspfieldnum": "2124",
                    "inspquestionnum": "1745",
                    "inspformnum": "1020",
                    "fieldtype": "SO",
                    "description": "Pedestrian detours",
                    "sequence": 1,
                    "required": false,
                    "initiallabel": "",
                    "endlabel": "",
                    "metername": "",
                    "metertype": "",
                    "showdate": false,
                    "showtime": false,
                    "doctype": "",
                    "visible": true,
                    "domainid": "",
                    "domaintype": "",
                    "options": [
                        {
                            "inspfieldnum": "2124",
                            "inspquestionnum": "1745",
                            "inspformnum": "1020",
                            "description": "Compliant",
                            "sequence": 1,
                            "inspectorfeedback": "",
                            "requireaction": false,
                            "color": "",
                            "icon": ""
                        },
                        {
                            "inspfieldnum": "2124",
                            "inspquestionnum": "1745",
                            "inspformnum": "1020",
                            "description": "Not Applicable",
                            "sequence": 2,
                            "inspectorfeedback": "",
                            "requireaction": false,
                            "color": "",
                            "icon": ""
                        },
                        {
                            "inspfieldnum": "2124",
                            "inspquestionnum": "1745",
                            "inspformnum": "1020",
                            "description": "Non-Compliant",
                            "sequence": 3,
                            "inspectorfeedback": "",
                            "requireaction": true,
                            "color": "",
                            "icon": ""
                        }
                    ]
                },
                {
                    "inspfieldnum": "2125",
                    "inspquestionnum": "1745",
                    "inspformnum": "1020",
                    "fieldtype": "TR",
                    "description": "Details",
                    "sequence": 2,
                    "required": false,
                    "initiallabel": "",
                    "endlabel": "",
                    "metername": "",
                    "metertype": "",
                    "showdate": false,
                    "showtime": false,
                    "doctype": "",
                    "visible": false,
                    "domainid": "",
                    "domaintype": "",
                    "options": []
                }
            ]
        },
        {
            "inspquestionnum": "1746",
            "inspformnum": "1020",
            "description": "No construction materials, equipment or debris posing trip hazards or falling objects risk.",
            "information": "",
            "groupid": 3,
            "sequence": 3,
            "groupseq": 3.003,
            "required": false,
            "fields": [
                {
                    "inspfieldnum": "2126",
                    "inspquestionnum": "1746",
                    "inspformnum": "1020",
                    "fieldtype": "SO",
                    "description": "Material and equipment safely stored",
                    "sequence": 1,
                    "required": false,
                    "initiallabel": "",
                    "endlabel": "",
                    "metername": "",
                    "metertype": "",
                    "showdate": false,
                    "showtime": false,
                    "doctype": "",
                    "visible": true,
                    "domainid": "",
                    "domaintype": "",
                    "options": [
                        {
                            "inspfieldnum": "2126",
                            "inspquestionnum": "1746",
                            "inspformnum": "1020",
                            "description": "Compliant",
                            "sequence": 1,
                            "inspectorfeedback": "",
                            "requireaction": false,
                            "color": "",
                            "icon": ""
                        },
                        {
                            "inspfieldnum": "2126",
                            "inspquestionnum": "1746",
                            "inspformnum": "1020",
                            "description": "Not Applicable",
                            "sequence": 2,
                            "inspectorfeedback": "",
                            "requireaction": false,
                            "color": "",
                            "icon": ""
                        },
                        {
                            "inspfieldnum": "2126",
                            "inspquestionnum": "1746",
                            "inspformnum": "1020",
                            "description": "Non-Compliant",
                            "sequence": 3,
                            "inspectorfeedback": "",
                            "requireaction": true,
                            "color": "",
                            "icon": ""
                        }
                    ]
                },
                {
                    "inspfieldnum": "2127",
                    "inspquestionnum": "1746",
                    "inspformnum": "1020",
                    "fieldtype": "TR",
                    "description": "Details",
                    "sequence": 2,
                    "required": false,
                    "initiallabel": "",
                    "endlabel": "",
                    "metername": "",
                    "metertype": "",
                    "showdate": false,
                    "showtime": false,
                    "doctype": "",
                    "visible": false,
                    "domainid": "",
                    "domaintype": "",
                    "options": []
                }
            ]
        },
        {
            "inspquestionnum": "1747",
            "inspformnum": "1020",
            "description": "Adequate lighting is present along public walkways adjacent to perimeter.",
            "information": "",
            "groupid": 3,
            "sequence": 4,
            "groupseq": 3.004,
            "required": false,
            "fields": [
                {
                    "inspfieldnum": "2128",
                    "inspquestionnum": "1747",
                    "inspformnum": "1020",
                    "fieldtype": "SO",
                    "description": "Adequate lighting",
                    "sequence": 1,
                    "required": false,
                    "initiallabel": "",
                    "endlabel": "",
                    "metername": "",
                    "metertype": "",
                    "showdate": false,
                    "showtime": false,
                    "doctype": "",
                    "visible": true,
                    "domainid": "",
                    "domaintype": "",
                    "options": [
                        {
                            "inspfieldnum": "2128",
                            "inspquestionnum": "1747",
                            "inspformnum": "1020",
                            "description": "Compliant",
                            "sequence": 1,
                            "inspectorfeedback": "",
                            "requireaction": false,
                            "color": "",
                            "icon": ""
                        },
                        {
                            "inspfieldnum": "2128",
                            "inspquestionnum": "1747",
                            "inspformnum": "1020",
                            "description": "Not Applicable",
                            "sequence": 2,
                            "inspectorfeedback": "",
                            "requireaction": false,
                            "color": "",
                            "icon": ""
                        },
                        {
                            "inspfieldnum": "2128",
                            "inspquestionnum": "1747",
                            "inspformnum": "1020",
                            "description": "Non-Compliant",
                            "sequence": 3,
                            "inspectorfeedback": "",
                            "requireaction": true,
                            "color": "",
                            "icon": ""
                        }
                    ]
                },
                {
                    "inspfieldnum": "2129",
                    "inspquestionnum": "1747",
                    "inspformnum": "1020",
                    "fieldtype": "TR",
                    "description": "Details",
                    "sequence": 2,
                    "required": false,
                    "initiallabel": "",
                    "endlabel": "",
                    "metername": "",
                    "metertype": "",
                    "showdate": false,
                    "showtime": false,
                    "doctype": "",
                    "visible": false,
                    "domainid": "",
                    "domaintype": "",
                    "options": []
                }
            ]
        },
        {
            "inspquestionnum": "1748",
            "inspformnum": "1020",
            "description": "Measures in place to prevent dust, excessive noise, or other pollutants impacting public areas",
            "information": "",
            "groupid": 3,
            "sequence": 5,
            "groupseq": 3.005,
            "required": false,
            "fields": [
                {
                    "inspfieldnum": "2130",
                    "inspquestionnum": "1748",
                    "inspformnum": "1020",
                    "fieldtype": "SO",
                    "description": "Dust/noise protection",
                    "sequence": 1,
                    "required": false,
                    "initiallabel": "",
                    "endlabel": "",
                    "metername": "",
                    "metertype": "",
                    "showdate": false,
                    "showtime": false,
                    "doctype": "",
                    "visible": true,
                    "domainid": "",
                    "domaintype": "",
                    "options": [
                        {
                            "inspfieldnum": "2130",
                            "inspquestionnum": "1748",
                            "inspformnum": "1020",
                            "description": "Compliant",
                            "sequence": 1,
                            "inspectorfeedback": "",
                            "requireaction": false,
                            "color": "",
                            "icon": ""
                        },
                        {
                            "inspfieldnum": "2130",
                            "inspquestionnum": "1748",
                            "inspformnum": "1020",
                            "description": "Not Applicable",
                            "sequence": 2,
                            "inspectorfeedback": "",
                            "requireaction": false,
                            "color": "",
                            "icon": ""
                        },
                        {
                            "inspfieldnum": "2130",
                            "inspquestionnum": "1748",
                            "inspformnum": "1020",
                            "description": "Non-Compliant",
                            "sequence": 3,
                            "inspectorfeedback": "",
                            "requireaction": true,
                            "color": "",
                            "icon": ""
                        }
                    ]
                },
                {
                    "inspfieldnum": "2131",
                    "inspquestionnum": "1748",
                    "inspformnum": "1020",
                    "fieldtype": "TR",
                    "description": "Details",
                    "sequence": 2,
                    "required": false,
                    "initiallabel": "",
                    "endlabel": "",
                    "metername": "",
                    "metertype": "",
                    "showdate": false,
                    "showtime": false,
                    "doctype": "",
                    "visible": false,
                    "domainid": "",
                    "domaintype": "",
                    "options": []
                }
            ]
        },
        {
            "inspquestionnum": "1749",
            "inspformnum": "1020",
            "description": "Signage related to site safety and public awareness is in good order, legible, and not obscured",
            "information": "",
            "groupid": 3,
            "sequence": 6,
            "groupseq": 3.006,
            "required": false,
            "fields": [
                {
                    "inspfieldnum": "2132",
                    "inspquestionnum": "1749",
                    "inspformnum": "1020",
                    "fieldtype": "SO",
                    "description": "Signage related to Site Safety",
                    "sequence": 1,
                    "required": false,
                    "initiallabel": "",
                    "endlabel": "",
                    "metername": "",
                    "metertype": "",
                    "showdate": false,
                    "showtime": false,
                    "doctype": "",
                    "visible": true,
                    "domainid": "",
                    "domaintype": "",
                    "options": [
                        {
                            "inspfieldnum": "2132",
                            "inspquestionnum": "1749",
                            "inspformnum": "1020",
                            "description": "Compliant",
                            "sequence": 1,
                            "inspectorfeedback": "",
                            "requireaction": false,
                            "color": "",
                            "icon": ""
                        },
                        {
                            "inspfieldnum": "2132",
                            "inspquestionnum": "1749",
                            "inspformnum": "1020",
                            "description": "Not Applicable",
                            "sequence": 2,
                            "inspectorfeedback": "",
                            "requireaction": false,
                            "color": "",
                            "icon": ""
                        },
                        {
                            "inspfieldnum": "2132",
                            "inspquestionnum": "1749",
                            "inspformnum": "1020",
                            "description": "Non-Compliant",
                            "sequence": 3,
                            "inspectorfeedback": "",
                            "requireaction": true,
                            "color": "",
                            "icon": ""
                        }
                    ]
                },
                {
                    "inspfieldnum": "2133",
                    "inspquestionnum": "1749",
                    "inspformnum": "1020",
                    "fieldtype": "TR",
                    "description": "Details",
                    "sequence": 2,
                    "required": false,
                    "initiallabel": "",
                    "endlabel": "",
                    "metername": "",
                    "metertype": "",
                    "showdate": false,
                    "showtime": false,
                    "doctype": "",
                    "visible": false,
                    "domainid": "",
                    "domaintype": "",
                    "options": []
                }
            ]
        },
        {
            "inspquestionnum": "1750",
            "inspformnum": "1020",
            "description": "General cleanliness of the visible perimeter area (no litter, waste, or discarded materials)",
            "information": "",
            "groupid": 4,
            "sequence": 1,
            "groupseq": 4.001,
            "required": false,
            "fields": [
                {
                    "inspfieldnum": "2134",
                    "inspquestionnum": "1750",
                    "inspformnum": "1020",
                    "fieldtype": "SO",
                    "description": "Cleanliness",
                    "sequence": 1,
                    "required": false,
                    "initiallabel": "",
                    "endlabel": "",
                    "metername": "",
                    "metertype": "",
                    "showdate": false,
                    "showtime": false,
                    "doctype": "",
                    "visible": true,
                    "domainid": "",
                    "domaintype": "",
                    "options": [
                        {
                            "inspfieldnum": "2134",
                            "inspquestionnum": "1750",
                            "inspformnum": "1020",
                            "description": "Compliant",
                            "sequence": 1,
                            "inspectorfeedback": "",
                            "requireaction": false,
                            "color": "",
                            "icon": ""
                        },
                        {
                            "inspfieldnum": "2134",
                            "inspquestionnum": "1750",
                            "inspformnum": "1020",
                            "description": "Not Applicable",
                            "sequence": 2,
                            "inspectorfeedback": "",
                            "requireaction": false,
                            "color": "",
                            "icon": ""
                        },
                        {
                            "inspfieldnum": "2134",
                            "inspquestionnum": "1750",
                            "inspformnum": "1020",
                            "description": "Non-Compliant",
                            "sequence": 3,
                            "inspectorfeedback": "",
                            "requireaction": true,
                            "color": "",
                            "icon": ""
                        }
                    ]
                },
                {
                    "inspfieldnum": "2135",
                    "inspquestionnum": "1750",
                    "inspformnum": "1020",
                    "fieldtype": "TR",
                    "description": "Details",
                    "sequence": 2,
                    "required": false,
                    "initiallabel": "",
                    "endlabel": "",
                    "metername": "",
                    "metertype": "",
                    "showdate": false,
                    "showtime": false,
                    "doctype": "",
                    "visible": false,
                    "domainid": "",
                    "domaintype": "",
                    "options": []
                }
            ]
        },
        {
            "inspquestionnum": "1751",
            "inspformnum": "1020",
            "description": "Waste bins/dumpsters are not overflowing and appear to be managed properly (lids closed)",
            "information": "",
            "groupid": 4,
            "sequence": 2,
            "groupseq": 4.002,
            "required": false,
            "fields": [
                {
                    "inspfieldnum": "2136",
                    "inspquestionnum": "1751",
                    "inspformnum": "1020",
                    "fieldtype": "SO",
                    "description": "Waste bins/dumpsters",
                    "sequence": 1,
                    "required": false,
                    "initiallabel": "",
                    "endlabel": "",
                    "metername": "",
                    "metertype": "",
                    "showdate": false,
                    "showtime": false,
                    "doctype": "",
                    "visible": true,
                    "domainid": "",
                    "domaintype": "",
                    "options": [
                        {
                            "inspfieldnum": "2136",
                            "inspquestionnum": "1751",
                            "inspformnum": "1020",
                            "description": "Compliant",
                            "sequence": 1,
                            "inspectorfeedback": "",
                            "requireaction": false,
                            "color": "",
                            "icon": ""
                        },
                        {
                            "inspfieldnum": "2136",
                            "inspquestionnum": "1751",
                            "inspformnum": "1020",
                            "description": "Not Applicable",
                            "sequence": 2,
                            "inspectorfeedback": "",
                            "requireaction": false,
                            "color": "",
                            "icon": ""
                        },
                        {
                            "inspfieldnum": "2136",
                            "inspquestionnum": "1751",
                            "inspformnum": "1020",
                            "description": "Non-Compliant",
                            "sequence": 3,
                            "inspectorfeedback": "",
                            "requireaction": true,
                            "color": "",
                            "icon": ""
                        }
                    ]
                },
                {
                    "inspfieldnum": "2137",
                    "inspquestionnum": "1751",
                    "inspformnum": "1020",
                    "fieldtype": "TR",
                    "description": "Details",
                    "sequence": 2,
                    "required": false,
                    "initiallabel": "",
                    "endlabel": "",
                    "metername": "",
                    "metertype": "",
                    "showdate": false,
                    "showtime": false,
                    "doctype": "",
                    "visible": false,
                    "domainid": "",
                    "domaintype": "",
                    "options": []
                }
            ]
        },
        {
            "inspquestionnum": "1752",
            "inspformnum": "1020",
            "description": "Erosion and sediment control measures (e.g., silt fending, straw bales) appear intact and functional",
            "information": "",
            "groupid": 4,
            "sequence": 3,
            "groupseq": 4.003,
            "required": false,
            "fields": [
                {
                    "inspfieldnum": "2138",
                    "inspquestionnum": "1752",
                    "inspformnum": "1020",
                    "fieldtype": "SO",
                    "description": "Erosion and sediment control",
                    "sequence": 1,
                    "required": false,
                    "initiallabel": "",
                    "endlabel": "",
                    "metername": "",
                    "metertype": "",
                    "showdate": false,
                    "showtime": false,
                    "doctype": "",
                    "visible": true,
                    "domainid": "",
                    "domaintype": "",
                    "options": [
                        {
                            "inspfieldnum": "2138",
                            "inspquestionnum": "1752",
                            "inspformnum": "1020",
                            "description": "Compliant",
                            "sequence": 1,
                            "inspectorfeedback": "",
                            "requireaction": false,
                            "color": "",
                            "icon": ""
                        },
                        {
                            "inspfieldnum": "2138",
                            "inspquestionnum": "1752",
                            "inspformnum": "1020",
                            "description": "Not Applicable",
                            "sequence": 2,
                            "inspectorfeedback": "",
                            "requireaction": false,
                            "color": "",
                            "icon": ""
                        },
                        {
                            "inspfieldnum": "2138",
                            "inspquestionnum": "1752",
                            "inspformnum": "1020",
                            "description": "Non-Compliant",
                            "sequence": 3,
                            "inspectorfeedback": "",
                            "requireaction": true,
                            "color": "",
                            "icon": ""
                        }
                    ]
                },
                {
                    "inspfieldnum": "2139",
                    "inspquestionnum": "1752",
                    "inspformnum": "1020",
                    "fieldtype": "TR",
                    "description": "Details",
                    "sequence": 2,
                    "required": false,
                    "initiallabel": "",
                    "endlabel": "",
                    "metername": "",
                    "metertype": "",
                    "showdate": false,
                    "showtime": false,
                    "doctype": "",
                    "visible": false,
                    "domainid": "",
                    "domaintype": "",
                    "options": []
                }
            ]
        },
        {
            "inspquestionnum": "1753",
            "inspformnum": "1020",
            "description": "No visible pooling of water or evidence of improper drainage causing issues outside perimeter",
            "information": "",
            "groupid": 4,
            "sequence": 4,
            "groupseq": 4.004,
            "required": false,
            "fields": [
                {
                    "inspfieldnum": "2140",
                    "inspquestionnum": "1753",
                    "inspformnum": "1020",
                    "fieldtype": "SO",
                    "description": "Pooling water, improper drainage",
                    "sequence": 1,
                    "required": false,
                    "initiallabel": "",
                    "endlabel": "",
                    "metername": "",
                    "metertype": "",
                    "showdate": false,
                    "showtime": false,
                    "doctype": "",
                    "visible": true,
                    "domainid": "",
                    "domaintype": "",
                    "options": [
                        {
                            "inspfieldnum": "2140",
                            "inspquestionnum": "1753",
                            "inspformnum": "1020",
                            "description": "Compliant",
                            "sequence": 1,
                            "inspectorfeedback": "",
                            "requireaction": false,
                            "color": "",
                            "icon": ""
                        },
                        {
                            "inspfieldnum": "2140",
                            "inspquestionnum": "1753",
                            "inspformnum": "1020",
                            "description": "Not Applicable",
                            "sequence": 2,
                            "inspectorfeedback": "",
                            "requireaction": false,
                            "color": "",
                            "icon": ""
                        },
                        {
                            "inspfieldnum": "2140",
                            "inspquestionnum": "1753",
                            "inspformnum": "1020",
                            "description": "Non-Compliant",
                            "sequence": 3,
                            "inspectorfeedback": "",
                            "requireaction": true,
                            "color": "",
                            "icon": ""
                        }
                    ]
                },
                {
                    "inspfieldnum": "2141",
                    "inspquestionnum": "1753",
                    "inspformnum": "1020",
                    "fieldtype": "TR",
                    "description": "Details",
                    "sequence": 2,
                    "required": false,
                    "initiallabel": "",
                    "endlabel": "",
                    "metername": "",
                    "metertype": "",
                    "showdate": false,
                    "showtime": false,
                    "doctype": "",
                    "visible": false,
                    "domainid": "",
                    "domaintype": "",
                    "options": []
                }
            ]
        },
        {
            "inspquestionnum": "1754",
            "inspformnum": "1020",
            "description": "Vehicle access points are free of excessive mud or debris tracking onto university roadways",
            "information": "",
            "groupid": 4,
            "sequence": 5,
            "groupseq": 4.005,
            "required": false,
            "fields": [
                {
                    "inspfieldnum": "2142",
                    "inspquestionnum": "1754",
                    "inspformnum": "1020",
                    "fieldtype": "SO",
                    "description": "Vehicle access points free of excessive mud/debris",
                    "sequence": 1,
                    "required": false,
                    "initiallabel": "",
                    "endlabel": "",
                    "metername": "",
                    "metertype": "",
                    "showdate": false,
                    "showtime": false,
                    "doctype": "",
                    "visible": true,
                    "domainid": "",
                    "domaintype": "",
                    "options": [
                        {
                            "inspfieldnum": "2142",
                            "inspquestionnum": "1754",
                            "inspformnum": "1020",
                            "description": "Compliant",
                            "sequence": 1,
                            "inspectorfeedback": "",
                            "requireaction": false,
                            "color": "",
                            "icon": ""
                        },
                        {
                            "inspfieldnum": "2142",
                            "inspquestionnum": "1754",
                            "inspformnum": "1020",
                            "description": "Not Applicable",
                            "sequence": 2,
                            "inspectorfeedback": "",
                            "requireaction": false,
                            "color": "",
                            "icon": ""
                        },
                        {
                            "inspfieldnum": "2142",
                            "inspquestionnum": "1754",
                            "inspformnum": "1020",
                            "description": "Non-Compliant",
                            "sequence": 3,
                            "inspectorfeedback": "",
                            "requireaction": true,
                            "color": "",
                            "icon": ""
                        }
                    ]
                },
                {
                    "inspfieldnum": "2143",
                    "inspquestionnum": "1754",
                    "inspformnum": "1020",
                    "fieldtype": "TR",
                    "description": "Details",
                    "sequence": 2,
                    "required": false,
                    "initiallabel": "",
                    "endlabel": "",
                    "metername": "",
                    "metertype": "",
                    "showdate": false,
                    "showtime": false,
                    "doctype": "",
                    "visible": false,
                    "domainid": "",
                    "domaintype": "",
                    "options": []
                }
            ]
        },
        {
            "inspquestionnum": "1755",
            "inspformnum": "1020",
            "description": "Required permits, health & safety notices, project info clearly displayed at main entry points",
            "information": "",
            "groupid": 5,
            "sequence": 1,
            "groupseq": 5.001,
            "required": false,
            "fields": [
                {
                    "inspfieldnum": "2144",
                    "inspquestionnum": "1755",
                    "inspformnum": "1020",
                    "fieldtype": "SO",
                    "description": "Notices and Project Information",
                    "sequence": 1,
                    "required": false,
                    "initiallabel": "",
                    "endlabel": "",
                    "metername": "",
                    "metertype": "",
                    "showdate": false,
                    "showtime": false,
                    "doctype": "",
                    "visible": true,
                    "domainid": "",
                    "domaintype": "",
                    "options": [
                        {
                            "inspfieldnum": "2144",
                            "inspquestionnum": "1755",
                            "inspformnum": "1020",
                            "description": "Compliant",
                            "sequence": 1,
                            "inspectorfeedback": "",
                            "requireaction": false,
                            "color": "",
                            "icon": ""
                        },
                        {
                            "inspfieldnum": "2144",
                            "inspquestionnum": "1755",
                            "inspformnum": "1020",
                            "description": "Not Applicable",
                            "sequence": 2,
                            "inspectorfeedback": "",
                            "requireaction": false,
                            "color": "",
                            "icon": ""
                        },
                        {
                            "inspfieldnum": "2144",
                            "inspquestionnum": "1755",
                            "inspformnum": "1020",
                            "description": "Non-Compliant",
                            "sequence": 3,
                            "inspectorfeedback": "",
                            "requireaction": true,
                            "color": "",
                            "icon": ""
                        }
                    ]
                },
                {
                    "inspfieldnum": "2145",
                    "inspquestionnum": "1755",
                    "inspformnum": "1020",
                    "fieldtype": "TR",
                    "description": "Details",
                    "sequence": 2,
                    "required": false,
                    "initiallabel": "",
                    "endlabel": "",
                    "metername": "",
                    "metertype": "",
                    "showdate": false,
                    "showtime": false,
                    "doctype": "",
                    "visible": false,
                    "domainid": "",
                    "domaintype": "",
                    "options": []
                }
            ]
        },
        {
            "inspquestionnum": "1756",
            "inspformnum": "1020",
            "description": "Emergency contact information for the contract and FMP is visible and up-to-date",
            "information": "",
            "groupid": 5,
            "sequence": 2,
            "groupseq": 5.002,
            "required": false,
            "fields": [
                {
                    "inspfieldnum": "2146",
                    "inspquestionnum": "1756",
                    "inspformnum": "1020",
                    "fieldtype": "SO",
                    "description": "Emergency and FMP contact information",
                    "sequence": 1,
                    "required": false,
                    "initiallabel": "",
                    "endlabel": "",
                    "metername": "",
                    "metertype": "",
                    "showdate": false,
                    "showtime": false,
                    "doctype": "",
                    "visible": true,
                    "domainid": "",
                    "domaintype": "",
                    "options": [
                        {
                            "inspfieldnum": "2146",
                            "inspquestionnum": "1756",
                            "inspformnum": "1020",
                            "description": "Compliant",
                            "sequence": 1,
                            "inspectorfeedback": "",
                            "requireaction": false,
                            "color": "",
                            "icon": ""
                        },
                        {
                            "inspfieldnum": "2146",
                            "inspquestionnum": "1756",
                            "inspformnum": "1020",
                            "description": "Not Applicable",
                            "sequence": 2,
                            "inspectorfeedback": "",
                            "requireaction": false,
                            "color": "",
                            "icon": ""
                        },
                        {
                            "inspfieldnum": "2146",
                            "inspquestionnum": "1756",
                            "inspformnum": "1020",
                            "description": "Non-Conpliant",
                            "sequence": 3,
                            "inspectorfeedback": "",
                            "requireaction": true,
                            "color": "",
                            "icon": ""
                        }
                    ]
                },
                {
                    "inspfieldnum": "2147",
                    "inspquestionnum": "1756",
                    "inspformnum": "1020",
                    "fieldtype": "TR",
                    "description": "Details",
                    "sequence": 2,
                    "required": false,
                    "initiallabel": "",
                    "endlabel": "",
                    "metername": "",
                    "metertype": "",
                    "showdate": false,
                    "showtime": false,
                    "doctype": "",
                    "visible": false,
                    "domainid": "",
                    "domaintype": "",
                    "options": []
                }
            ]
        },
        {
            "inspquestionnum": "1757",
            "inspformnum": "1020",
            "description": "External signage clearly displays the construction company name and primary contact details",
            "information": "",
            "groupid": 5,
            "sequence": 3,
            "groupseq": 5.003,
            "required": false,
            "fields": [
                {
                    "inspfieldnum": "2148",
                    "inspquestionnum": "1757",
                    "inspformnum": "1020",
                    "fieldtype": "SO",
                    "description": "Construction company primary contact details",
                    "sequence": 1,
                    "required": false,
                    "initiallabel": "",
                    "endlabel": "",
                    "metername": "",
                    "metertype": "",
                    "showdate": false,
                    "showtime": false,
                    "doctype": "",
                    "visible": true,
                    "domainid": "",
                    "domaintype": "",
                    "options": [
                        {
                            "inspfieldnum": "2148",
                            "inspquestionnum": "1757",
                            "inspformnum": "1020",
                            "description": "Compliant",
                            "sequence": 1,
                            "inspectorfeedback": "",
                            "requireaction": false,
                            "color": "",
                            "icon": ""
                        },
                        {
                            "inspfieldnum": "2148",
                            "inspquestionnum": "1757",
                            "inspformnum": "1020",
                            "description": "Not Applicable",
                            "sequence": 2,
                            "inspectorfeedback": "",
                            "requireaction": false,
                            "color": "",
                            "icon": ""
                        },
                        {
                            "inspfieldnum": "2148",
                            "inspquestionnum": "1757",
                            "inspformnum": "1020",
                            "description": "Non-Compliant",
                            "sequence": 3,
                            "inspectorfeedback": "",
                            "requireaction": true,
                            "color": "",
                            "icon": ""
                        }
                    ]
                },
                {
                    "inspfieldnum": "2149",
                    "inspquestionnum": "1757",
                    "inspformnum": "1020",
                    "fieldtype": "TR",
                    "description": "Details",
                    "sequence": 2,
                    "required": false,
                    "initiallabel": "",
                    "endlabel": "",
                    "metername": "",
                    "metertype": "",
                    "showdate": false,
                    "showtime": false,
                    "doctype": "",
                    "visible": false,
                    "domainid": "",
                    "domaintype": "",
                    "options": []
                }
            ]
        },
        {
            "inspquestionnum": "1758",
            "inspformnum": "1020",
            "description": "Site Security and Demarcation",
            "information": "",
            "groupid": 2,
            "sequence": 0,
            "groupseq": 2,
            "required": false,
            "fields": []
        },
        {
            "inspquestionnum": "1759",
            "inspformnum": "1020",
            "description": "Public Safety and Access (Considering \"Sudbury Legal Case\" Implications",
            "information": "",
            "groupid": 3,
            "sequence": 0,
            "groupseq": 3,
            "required": false,
            "fields": []
        },
        {
            "inspquestionnum": "1760",
            "inspformnum": "1020",
            "description": "Site Orderliness and Environmental Controls",
            "information": "",
            "groupid": 4,
            "sequence": 0,
            "groupseq": 4,
            "required": false,
            "fields": []
        },
        {
            "inspquestionnum": "1761",
            "inspformnum": "1020",
            "description": "Regulatory and Information Displays",
            "information": "",
            "groupid": 5,
            "sequence": 0,
            "groupseq": 5,
            "required": false,
            "fields": []
        },
        {
            "inspquestionnum": "1762",
            "inspformnum": "1020",
            "description": "Enter today's date and time",
            "information": "",
            "sequence": 6,
            "groupseq": 6,
            "required": false,
            "fields": [
                {
                    "inspfieldnum": "2150",
                    "inspquestionnum": "1762",
                    "inspformnum": "1020",
                    "fieldtype": "DT",
                    "description": "Enter today's date and time",
                    "sequence": 1,
                    "required": true,
                    "initiallabel": "",
                    "endlabel": "",
                    "metername": "",
                    "metertype": "",
                    "showdate": false,
                    "showtime": false,
                    "doctype": "",
                    "visible": true,
                    "domainid": "",
                    "domaintype": "",
                    "options": []
                }
            ]
        }
    ],
    "cascadeoptions": [
        {
            "inspcascadeoptionnum": "1142",
            "inspformnum": "1020",
            "srcquestion": "1740",
            "srcfield": "2114",
            "srctxtresponse": "Non-Compliant",
            "tgtquestion": "1740",
            "tgtfield": "2115",
            "visible": true,
            "required": true,
            "inspectorfeedback": "",
            "showmessage": false,
            "operator1": "",
            "operator2": "",
            "number1": 0,
            "number2": 0,
            "requireaction": false
        },
        {
            "inspcascadeoptionnum": "1143",
            "inspformnum": "1020",
            "srcquestion": "1742",
            "srcfield": "2118",
            "srctxtresponse": "Non-Compliant",
            "tgtquestion": "1742",
            "tgtfield": "2119",
            "visible": true,
            "required": true,
            "inspectorfeedback": "",
            "showmessage": false,
            "operator1": "",
            "operator2": "",
            "number1": 0,
            "number2": 0,
            "requireaction": false
        },
        {
            "inspcascadeoptionnum": "1144",
            "inspformnum": "1020",
            "srcquestion": "1743",
            "srcfield": "2120",
            "srctxtresponse": "Non-Compliant",
            "tgtquestion": "1743",
            "tgtfield": "2121",
            "visible": true,
            "required": true,
            "inspectorfeedback": "",
            "showmessage": false,
            "operator1": "",
            "operator2": "",
            "number1": 0,
            "number2": 0,
            "requireaction": false
        },
        {
            "inspcascadeoptionnum": "1145",
            "inspformnum": "1020",
            "srcquestion": "1744",
            "srcfield": "2122",
            "srctxtresponse": "Non-Compliant",
            "tgtquestion": "1744",
            "tgtfield": "2123",
            "visible": true,
            "required": true,
            "inspectorfeedback": "",
            "showmessage": false,
            "operator1": "",
            "operator2": "",
            "number1": 0,
            "number2": 0,
            "requireaction": false
        },
        {
            "inspcascadeoptionnum": "1146",
            "inspformnum": "1020",
            "srcquestion": "1745",
            "srcfield": "2124",
            "srctxtresponse": "Non-Compliant",
            "tgtquestion": "1745",
            "tgtfield": "2125",
            "visible": true,
            "required": true,
            "inspectorfeedback": "",
            "showmessage": false,
            "operator1": "",
            "operator2": "",
            "number1": 0,
            "number2": 0,
            "requireaction": false
        },
        {
            "inspcascadeoptionnum": "1147",
            "inspformnum": "1020",
            "srcquestion": "1746",
            "srcfield": "2126",
            "srctxtresponse": "Non-Compliant",
            "tgtquestion": "1746",
            "tgtfield": "2127",
            "visible": true,
            "required": true,
            "inspectorfeedback": "",
            "showmessage": false,
            "operator1": "",
            "operator2": "",
            "number1": 0,
            "number2": 0,
            "requireaction": false
        },
        {
            "inspcascadeoptionnum": "1148",
            "inspformnum": "1020",
            "srcquestion": "1747",
            "srcfield": "2128",
            "srctxtresponse": "Non-Compliant",
            "tgtquestion": "1747",
            "tgtfield": "2129",
            "visible": true,
            "required": true,
            "inspectorfeedback": "",
            "showmessage": false,
            "operator1": "",
            "operator2": "",
            "number1": 0,
            "number2": 0,
            "requireaction": false
        },
        {
            "inspcascadeoptionnum": "1149",
            "inspformnum": "1020",
            "srcquestion": "1748",
            "srcfield": "2130",
            "srctxtresponse": "Non-Compliant",
            "tgtquestion": "1748",
            "tgtfield": "2131",
            "visible": true,
            "required": true,
            "inspectorfeedback": "",
            "showmessage": false,
            "operator1": "",
            "operator2": "",
            "number1": 0,
            "number2": 0,
            "requireaction": false
        },
        {
            "inspcascadeoptionnum": "1150",
            "inspformnum": "1020",
            "srcquestion": "1749",
            "srcfield": "2132",
            "srctxtresponse": "Non-Compliant",
            "tgtquestion": "1749",
            "tgtfield": "2133",
            "visible": true,
            "required": true,
            "inspectorfeedback": "",
            "showmessage": false,
            "operator1": "",
            "operator2": "",
            "number1": 0,
            "number2": 0,
            "requireaction": false
        },
        {
            "inspcascadeoptionnum": "1151",
            "inspformnum": "1020",
            "srcquestion": "1750",
            "srcfield": "2134",
            "srctxtresponse": "Non-Compliant",
            "tgtquestion": "1750",
            "tgtfield": "2135",
            "visible": true,
            "required": true,
            "inspectorfeedback": "",
            "showmessage": false,
            "operator1": "",
            "operator2": "",
            "number1": 0,
            "number2": 0,
            "requireaction": false
        },
        {
            "inspcascadeoptionnum": "1152",
            "inspformnum": "1020",
            "srcquestion": "1751",
            "srcfield": "2136",
            "srctxtresponse": "Non-Compliant",
            "tgtquestion": "1751",
            "tgtfield": "2137",
            "visible": true,
            "required": true,
            "inspectorfeedback": "",
            "showmessage": false,
            "operator1": "",
            "operator2": "",
            "number1": 0,
            "number2": 0,
            "requireaction": false
        },
        {
            "inspcascadeoptionnum": "1153",
            "inspformnum": "1020",
            "srcquestion": "1752",
            "srcfield": "2138",
            "srctxtresponse": "Non-Compliant",
            "tgtquestion": "1752",
            "tgtfield": "2139",
            "visible": true,
            "required": true,
            "inspectorfeedback": "",
            "showmessage": false,
            "operator1": "",
            "operator2": "",
            "number1": 0,
            "number2": 0,
            "requireaction": false
        },
        {
            "inspcascadeoptionnum": "1154",
            "inspformnum": "1020",
            "srcquestion": "1753",
            "srcfield": "2140",
            "srctxtresponse": "Non-Compliant",
            "tgtquestion": "1753",
            "tgtfield": "2141",
            "visible": true,
            "required": true,
            "inspectorfeedback": "",
            "showmessage": false,
            "operator1": "",
            "operator2": "",
            "number1": 0,
            "number2": 0,
            "requireaction": false
        },
        {
            "inspcascadeoptionnum": "1155",
            "inspformnum": "1020",
            "srcquestion": "1754",
            "srcfield": "2142",
            "srctxtresponse": "Non-Compliant",
            "tgtquestion": "1754",
            "tgtfield": "2143",
            "visible": true,
            "required": true,
            "inspectorfeedback": "",
            "showmessage": false,
            "operator1": "",
            "operator2": "",
            "number1": 0,
            "number2": 0,
            "requireaction": false
        },
        {
            "inspcascadeoptionnum": "1156",
            "inspformnum": "1020",
            "srcquestion": "1755",
            "srcfield": "2144",
            "srctxtresponse": "Non-Compliant",
            "tgtquestion": "1755",
            "tgtfield": "2145",
            "visible": true,
            "required": true,
            "inspectorfeedback": "",
            "showmessage": false,
            "operator1": "",
            "operator2": "",
            "number1": 0,
            "number2": 0,
            "requireaction": false
        },
        {
            "inspcascadeoptionnum": "1157",
            "inspformnum": "1020",
            "srcquestion": "1756",
            "srcfield": "2146",
            "srctxtresponse": "Non-Conpliant",
            "tgtquestion": "1756",
            "tgtfield": "2147",
            "visible": true,
            "required": true,
            "inspectorfeedback": "",
            "showmessage": false,
            "operator1": "",
            "operator2": "",
            "number1": 0,
            "number2": 0,
            "requireaction": false
        }
    ],
    "scripts": []
}